pg_python_sdk/__init__.py
pg_python_sdk/payment_gateway_client.py
pg_python_sdk/payment_gateway_request.py
pg_python_sdk/payment_gateway_response.py
pg_python_sdk-0.0.14.dist-info/LICENSE
pg_python_sdk-0.0.14.dist-info/METADATA
pg_python_sdk-0.0.14.dist-info/WHEEL
pg_python_sdk-0.0.14.dist-info/top_level.txt
pg_python_sdk-0.0.14.dist-info/RECORD
