Metadata-Version: 2.1
Name: pg-python-sdk
Version: 0.0.14
Summary: Python SDK for the Payment Gateway
Home-page: https://github.com/abdulmejidshemsu/pg-python-sdk
Author: Abdulmejid Shemsu
Author-email: abdudlh1@gmail.com
Project-URL: Bug Tracker, https://github.com/abdulmejidshemsu/pg-python-sdk/issues
Classifier: Programming Language :: Python :: 3
Classifier: License :: OSI Approved :: MIT License
Classifier: Operating System :: OS Independent
Requires-Python: >=3.6
License-File: LICENSE
Requires-Dist: requests
